{
  "sufixos_unidade": [
    "kg",
    "g",
    "l",
    "ml",
    "cx",
    "un",
    "und",
    "lata",
    "pct"
  ],
  "prefixos_marca": [
    "seara",
    "sadia",
    "perdigao",
    "aurora",
    "tio",
    "uncle"
  ],
  "palavras_estado": [
    "fresco",
    "fresh",
    "congelado",
    "frozen",
    "seco",
    "dry"
  ],
  "termos_qualidade": [
    "premium",
    "select",
    "extra",
    "especial",
    "gourmet"
  ],
  "termos_origem": [
    "atlantico",
    "pacifico",
    "brasileiro",
    "nacional",
    "importado"
  ],
  "palavras_ignorar": [
    "de",
    "da",
    "do",
    "com",
    "para",
    "em",
    "no",
    "na"
  ],
  "sinonimos_regionais": {
    "macaxeira": "mandioca",
    "aipim": "mandioca",
    "jerimum": "abobora",
    "chuchu": "chuchu"
  }
}